MANIFEST.in
README.rst
requirements.txt
setup.cfg
setup.py
kotti_google_analytics/__init__.py
kotti_google_analytics/__init__.pyc
kotti_google_analytics/fanstatic.py
kotti_google_analytics/fanstatic.pyc
kotti_google_analytics/populate.py
kotti_google_analytics/populate.pyc
kotti_google_analytics/resources.py
kotti_google_analytics/resources.pyc
kotti_google_analytics.egg-info/PKG-INFO
kotti_google_analytics.egg-info/SOURCES.txt
kotti_google_analytics.egg-info/dependency_links.txt
kotti_google_analytics.egg-info/entry_points.txt
kotti_google_analytics.egg-info/not-zip-safe
kotti_google_analytics.egg-info/requires.txt
kotti_google_analytics.egg-info/top_level.txt
kotti_google_analytics/alembic/script.py.mako
kotti_google_analytics/locale/.gitkeep
kotti_google_analytics/static/Chart.min.js
kotti_google_analytics/static/active-users.js
kotti_google_analytics/static/analytics.png
kotti_google_analytics/static/chartjs-visualizations.css
kotti_google_analytics/static/date-range-selector.js
kotti_google_analytics/static/embed.js
kotti_google_analytics/static/index.css
kotti_google_analytics/static/moment.min.js
kotti_google_analytics/static/scripts.js
kotti_google_analytics/static/scripts.min.js
kotti_google_analytics/static/styles.css
kotti_google_analytics/static/styles.min.css
kotti_google_analytics/static/view-selector2.js
kotti_google_analytics/static/widget.js
kotti_google_analytics/templates/analytics.pt
kotti_google_analytics/templates/controlpanel.pt
kotti_google_analytics/templates/redirect_result.pt
kotti_google_analytics/templates/tracking_code.pt
kotti_google_analytics/tests/conftest.py
kotti_google_analytics/tests/test_functional.py
kotti_google_analytics/tests/test_resources.py
kotti_google_analytics/tests/test_view.py
kotti_google_analytics/views/__init__.py
kotti_google_analytics/views/__init__.pyc
kotti_google_analytics/views/edit.py
kotti_google_analytics/views/edit.pyc
kotti_google_analytics/views/view.py
kotti_google_analytics/views/view.pyc