Metadata-Version: 1.1
Name: kotti-google-analytics
Version: 1.1.21
Summary: Google Analytics for Kotti
Home-page: https://github.com/b4oshany/kotti_google_analytics
Author: Oshane Bailey
Author-email: b4.oshany@gmail.com
License: BSD-derived (http://www.repoze.org/LICENSE.txt)
Keywords: google analytics kotti web cms wcms pylons pyramidsqlalchemy bootstrap tracking users
Platform: UNKNOWN
Classifier: Programming Language :: Python
Classifier: Programming Language :: Python :: 2.7
Classifier: Framework :: Pylons
Classifier: Topic :: Internet :: WWW/HTTP
Classifier: Topic :: Internet :: WWW/HTTP :: Dynamic Content
Classifier: Topic :: Internet :: WWW/HTTP :: WSGI :: Application
Classifier: License :: Repoze Public License
